pypetka_script/__init__.py
pypetka_script/example_github.py
pypetka_script/example_pypi.py
pypetka_script/pypetka_script.py
pypetka_script-4.0.0.dist-info/licenses/LICENSE
pypetka_script-4.0.0.dist-info/METADATA
pypetka_script-4.0.0.dist-info/WHEEL
pypetka_script-4.0.0.dist-info/top_level.txt
pypetka_script-4.0.0.dist-info/zip-safe
pypetka_script-4.0.0.dist-info/RECORD
