Metadata-Version: 2.4
Name: PyPetka-Script
Version: 4.0.0
Summary: Русскоязычная библиотека Python с 150+ функциями для студентов и разработчиков. Упрощение работы с Python, математикой, шифрованием и алгоритмами.
Home-page: https://github.com/IlyaChaek/PyPetka-Script
Author: Chorelin
Author-email: miheevila6@gmail.com
License: MIT
Project-URL: Homepage, https://github.com/IlyaChaek/PyPetka-Script
Project-URL: Documentation, https://github.com/IlyaChaek/PyPetka-Script/blob/main/README.md
Project-URL: Bug Reports, https://github.com/IlyaChaek/PyPetka-Script/issues
Project-URL: Source Code, https://github.com/IlyaChaek/PyPetka-Script
Project-URL: Changelog, https://github.com/IlyaChaek/PyPetka-Script/releases
Keywords: python,russian,education,library,students,math,cryptography,algorithms,pypetka,programming,development,tools,utilities
Platform: any
Classifier: Programming Language :: Python :: 3
Classifier: Programming Language :: Python :: 3.6
Classifier: Programming Language :: Python :: 3.7
Classifier: Programming Language :: Python :: 3.8
Classifier: Programming Language :: Python :: 3.9
Classifier: Programming Language :: Python :: 3.10
Classifier: Programming Language :: Python :: 3.11
Classifier: Programming Language :: Python :: 3.12
Classifier: Programming Language :: Python :: 3.13
Classifier: License :: OSI Approved :: MIT License
Classifier: Operating System :: OS Independent
Classifier: Operating System :: Microsoft :: Windows
Classifier: Operating System :: POSIX :: Linux
Classifier: Operating System :: MacOS
Classifier: Development Status :: 5 - Production/Stable
Classifier: Intended Audience :: Education
Classifier: Intended Audience :: Developers
Classifier: Intended Audience :: End Users/Desktop
Classifier: Topic :: Education
Classifier: Topic :: Software Development :: Libraries :: Python Modules
Classifier: Topic :: Scientific/Engineering :: Mathematics
Classifier: Topic :: Security :: Cryptography
Classifier: Topic :: Utilities
Classifier: Natural Language :: Russian
Requires-Python: >=3.6
License-File: LICENSE
Provides-Extra: dev
Requires-Dist: twine>=4.0.0; extra == "dev"
Requires-Dist: wheel>=0.40.0; extra == "dev"
Dynamic: author
Dynamic: author-email
Dynamic: classifier
Dynamic: description
Dynamic: description-content-type
Dynamic: home-page
Dynamic: keywords
Dynamic: license
Dynamic: license-file
Dynamic: platform
Dynamic: project-url
Dynamic: provides-extra
Dynamic: requires-python
Dynamic: summary
